orh/__init__.py
orh/main.py
orh/cli/__init__.py
orh/cli/clean.py
orh/cli/convert.py
orh/cli/merge.py
odoo_reporting_helper-0.0.2.dist-info/METADATA
odoo_reporting_helper-0.0.2.dist-info/WHEEL
odoo_reporting_helper-0.0.2.dist-info/entry_points.txt
odoo_reporting_helper-0.0.2.dist-info/top_level.txt
odoo_reporting_helper-0.0.2.dist-info/RECORD
