Metadata-Version: 2.1
Name: odoo-reporting-helper
Version: 0.0.2
Summary: Odoo Reporting Helper
Home-page: https://github.com/royaurelien/odoo-reporting-helper
Author: Aurelien ROY
Author-email: roy.aurelien@gmail.com
License: BSD 2-clause
Classifier: Development Status :: 3 - Alpha
Classifier: Intended Audience :: Developers
Classifier: Topic :: Software Development :: Build Tools
Classifier: License :: OSI Approved :: BSD License
Classifier: Programming Language :: Python :: 3
Classifier: Programming Language :: Python :: 3.8
Classifier: Programming Language :: Python :: 3.9
Classifier: Programming Language :: Python :: 3.10
Classifier: Programming Language :: Python :: 3.11
Requires-Python: >=3.8
Requires-Dist: click
Requires-Dist: lxml
Requires-Dist: pdfkit
Requires-Dist: requests
